{"buttons":[{"buttonId":4,"id":98,"posX":3,"posY":2,"rotation":1},{"buttonId":5,"id":98,"posX":5,"posY":2,"rotation":2},{"buttonId":6,"id":98,"posX":5,"posY":3,"rotation":3},{"buttonId":3,"id":98,"posX":2,"posY":4,"rotation":0},{"buttonId":7,"id":98,"posX":6,"posY":4,"rotation":0},{"buttonId":2,"id":98,"posX":1,"posY":6,"rotation":3},{"buttonId":1,"id":98,"posX":1,"posY":6,"rotation":2}],"cubes":[{"id":99,"posX":3,"posY":6,"rotation":2}],"goal":{"buttonList":[],"id":64,"posX":7,"posY":6,"rotation":2},"map_size":{"col":8,"row":9},"player":{"id":112,"posX":5,"posY":6,"rotation":2},"tiles":[{"id":49,"posX":0,"posY":0,"rotation":2},{"id":49,"posX":1,"posY":0,"rotation":2},{"id":49,"posX":2,"posY":0,"rotation":2},{"id":49,"posX":3,"posY":0,"rotation":2},{"id":49,"posX":4,"posY":0,"rotation":2},{"id":49,"posX":5,"posY":0,"rotation":2},{"id":49,"posX":6,"posY":0,"rotation":2},{"id":49,"posX":7,"posY":0,"rotation":2},{"id":49,"posX":8,"posY":0,"rotation":2},{"id":49,"posX":0,"posY":1,"rotation":2},{"id":49,"posX":8,"posY":1,"rotation":2},{"id":49,"posX":0,"posY":2,"rotation":2},{"id":49,"posX":8,"posY":2,"rotation":2},{"id":49,"posX":0,"posY":3,"rotation":2},{"id":49,"posX":8,"posY":3,"rotation":2},{"id":49,"posX":0,"posY":4,"rotation":2},{"id":49,"posX":8,"posY":4,"rotation":2},{"id":49,"posX":0,"posY":5,"rotation":2},{"id":49,"posX":8,"posY":5,"rotation":2},{"id":49,"posX":0,"posY":6,"rotation":2},{"id":49,"posX":8,"posY":6,"rotation":2},{"id":49,"posX":0,"posY":7,"rotation":2},{"id":49,"posX":1,"posY":7,"rotation":2},{"id":49,"posX":2,"posY":7,"rotation":2},{"id":49,"posX":3,"posY":7,"rotation":2},{"id":49,"posX":4,"posY":7,"rotation":2},{"id":49,"posX":5,"posY":7,"rotation":2},{"id":49,"posX":6,"posY":7,"rotation":2},{"id":49,"posX":7,"posY":7,"rotation":2},{"id":49,"posX":8,"posY":7,"rotation":2}]}